opensfc/__init__.py
opensfc-0.0.1.dist-info/licenses/LICENSE
opensfc-0.0.1.dist-info/METADATA
opensfc-0.0.1.dist-info/WHEEL
opensfc-0.0.1.dist-info/top_level.txt
opensfc-0.0.1.dist-info/RECORD
